NulledAPI/__init__.py
NulledAPI/nulledapi.py
NulledAPI-1.2.dist-info/METADATA
NulledAPI-1.2.dist-info/WHEEL
NulledAPI-1.2.dist-info/top_level.txt
NulledAPI-1.2.dist-info/RECORD
