Metadata-Version: 2.1
Name: NulledAPI
Version: 1.2
Summary: NulledAPI - UnOfficial Nulled API
Home-page: https://www.nulled.to/user/4103370-m3gz
Author: M3GZ
Author-email: megzfromnulled@gmail.com
License: UNKNOWN
Platform: UNKNOWN
Classifier: Development Status :: 5 - Production/Stable
Classifier: Programming Language :: Python :: 3
Classifier: Intended Audience :: Developers
Classifier: Topic :: Utilities
Requires-Dist: cloudscraper
